CongNixiangGongchengDeJiaoduLaikanCKanxue/README.md
CongNixiangGongchengDeJiaoduLaikanCKanxue/__init__.py
CongNixiangGongchengDeJiaoduLaikanCKanxue/__main__.py
CongNixiangGongchengDeJiaoduLaikanCKanxue/file.epub
CongNixiangGongchengDeJiaoduLaikanCKanxue/index.html
CongNixiangGongchengDeJiaoduLaikanCKanxue/css/__init__.py
CongNixiangGongchengDeJiaoduLaikanCKanxue/css/annotations.css
CongNixiangGongchengDeJiaoduLaikanCKanxue/css/main.css
CongNixiangGongchengDeJiaoduLaikanCKanxue/css/normalize.css
CongNixiangGongchengDeJiaoduLaikanCKanxue/css/popup.css
CongNixiangGongchengDeJiaoduLaikanCKanxue/font/__init__.py
CongNixiangGongchengDeJiaoduLaikanCKanxue/font/fontello.eot
CongNixiangGongchengDeJiaoduLaikanCKanxue/font/fontello.svg
CongNixiangGongchengDeJiaoduLaikanCKanxue/font/fontello.ttf
CongNixiangGongchengDeJiaoduLaikanCKanxue/font/fontello.woff
CongNixiangGongchengDeJiaoduLaikanCKanxue/img/__init__.py
CongNixiangGongchengDeJiaoduLaikanCKanxue/img/annotator-glyph-sprite.png
CongNixiangGongchengDeJiaoduLaikanCKanxue/img/annotator-icon-sprite.png
CongNixiangGongchengDeJiaoduLaikanCKanxue/img/apple-touch-icon.png
CongNixiangGongchengDeJiaoduLaikanCKanxue/img/cancelfullscreen.png
CongNixiangGongchengDeJiaoduLaikanCKanxue/img/close.png
CongNixiangGongchengDeJiaoduLaikanCKanxue/img/fullscreen.png
CongNixiangGongchengDeJiaoduLaikanCKanxue/img/loader.gif
CongNixiangGongchengDeJiaoduLaikanCKanxue/img/menu-icon.png
CongNixiangGongchengDeJiaoduLaikanCKanxue/img/save.png
CongNixiangGongchengDeJiaoduLaikanCKanxue/img/saved.png
CongNixiangGongchengDeJiaoduLaikanCKanxue/img/settings-s.png
CongNixiangGongchengDeJiaoduLaikanCKanxue/img/settings.png
CongNixiangGongchengDeJiaoduLaikanCKanxue/img/star.png
CongNixiangGongchengDeJiaoduLaikanCKanxue/js/__init__.py
CongNixiangGongchengDeJiaoduLaikanCKanxue/js/epub.js
CongNixiangGongchengDeJiaoduLaikanCKanxue/js/epub.min.js
CongNixiangGongchengDeJiaoduLaikanCKanxue/js/epub.min.map
CongNixiangGongchengDeJiaoduLaikanCKanxue/js/hooks.min.js
cong_nixiang_gongcheng_de_jiaodu_laikan_c_kanxue-2024.3.2.0.dist-info/METADATA
cong_nixiang_gongcheng_de_jiaodu_laikan_c_kanxue-2024.3.2.0.dist-info/WHEEL
cong_nixiang_gongcheng_de_jiaodu_laikan_c_kanxue-2024.3.2.0.dist-info/entry_points.txt
cong_nixiang_gongcheng_de_jiaodu_laikan_c_kanxue-2024.3.2.0.dist-info/top_level.txt
cong_nixiang_gongcheng_de_jiaodu_laikan_c_kanxue-2024.3.2.0.dist-info/RECORD
